README.txt
setup.cfg
setup.py
Products/__init__.py
Products.Mlango.egg-info/PKG-INFO
Products.Mlango.egg-info/SOURCES.txt
Products.Mlango.egg-info/dependency_links.txt
Products.Mlango.egg-info/entry_points.txt
Products.Mlango.egg-info/namespace_packages.txt
Products.Mlango.egg-info/not-zip-safe
Products.Mlango.egg-info/requires.txt
Products.Mlango.egg-info/top_level.txt
Products/Mlango/README.txt
Products/Mlango/TODO
Products/Mlango/__init__.py
Products/Mlango/config.py
Products/Mlango/configure.zcml
Products/Mlango/overrides.zcml
Products/Mlango/profiles.zcml
Products/Mlango/refresh.txt
Products/Mlango/setuphandlers.py
Products/Mlango/tests.py
Products/Mlango/version.txt
Products/Mlango/content/MlangoDashboard.py
Products/Mlango/content/__init__.py
Products/Mlango/content/interfaces.py
Products/Mlango/i18n/generated.pot
Products/Mlango/portlets/__init__.py
Products/Mlango/portlets/configure.zcml
Products/Mlango/portlets/interfaces.py
Products/Mlango/portlets/managerrenderer.py
Products/Mlango/portlets/wrapper.py
Products/Mlango/portlets/browser/__init__.py
Products/Mlango/portlets/browser/configure.zcml
Products/Mlango/portlets/browser/kss.py
Products/Mlango/portlets/browser/templates/contextmlangodashboard.pt
Products/Mlango/portlets/browser/templates/dashboard-column.pt
Products/Mlango/portlets/browser/templates/effects.js
Products/Mlango/portlets/browser/templates/jquery-ui-personalized-1.6rc2.min.js
Products/Mlango/portlets/browser/templates/manage-context-dashboard.pt
Products/Mlango/portlets/browser/templates/mlango.js
Products/Mlango/portlets/browser/templates/mlango.kss
Products/Mlango/portlets/browser/templates/mlangodashboard.pt
Products/Mlango/portlets/browser/templates/portlet-macros.pt
Products/Mlango/portlets/browser/templates/portlet.pt
Products/Mlango/profiles/default/Mlango_marker.txt
Products/Mlango/profiles/default/actionicons.xml
Products/Mlango/profiles/default/controlpanel.xml
Products/Mlango/profiles/default/cssregistry.xml
Products/Mlango/profiles/default/factorytool.xml
Products/Mlango/profiles/default/import_steps.xml
Products/Mlango/profiles/default/jsregistry.xml
Products/Mlango/profiles/default/kssregistry.xml
Products/Mlango/profiles/default/portlets.xml
Products/Mlango/profiles/default/skins.xml
Products/Mlango/profiles/default/types.xml
