Metadata-Version: 1.0
Name: Products.Mlango
Version: 2.2.1dev-r83772
Summary: Mlango is a desktop dashboard implementation similar to the Google dashboard (iGoogle).
Home-page: http://www.gw20e.com/
Author: Goldmund, Wyldebeast & Wunderliebe
Author-email: mlango@gw20e.com
License: GPL
Platform: UNKNOWN
Classifier: Development Status :: 4 - Beta
Classifier: Operating System :: OS Independent
Classifier: Programming Language :: Python
Classifier: Topic :: Software Development :: Libraries :: Python Modules
